app/__init__.py
flask/__init__.py
flask/__main__.py
flask/_compat.c
flask/_compat.py
flask/app.c
flask/app.py
flask/blueprints.c
flask/blueprints.py
flask/cli.c
flask/cli.py
flask/config.c
flask/config.py
flask/ctx.c
flask/ctx.py
flask/debughelpers.c
flask/debughelpers.py
flask/globals.c
flask/globals.py
flask/helpers.c
flask/helpers.py
flask/logging.c
flask/logging.py
flask/sessions.c
flask/sessions.py
flask/setup.py
flask/signals.c
flask/signals.py
flask/templating.c
flask/templating.py
flask/testing.c
flask/testing.py
flask/views.c
flask/views.py
flask/wrappers.c
flask/wrappers.py
flask/json/__init__.cp37-win_amd64.pyd
flask/json/__init__.py
flask/json/tag.cp37-win_amd64.pyd
flask/json/tag.py
flask_restful/representations/json.cp37-win_amd64.pyd
flask_restful/utils/cors.cp37-win_amd64.pyd
flask_restful/utils/crypto.cp37-win_amd64.pyd
jtmorrisbytes/__init__.py
jtmorrisbytes/regex.c
jtmorrisbytes/test.py
jtmorrisbytes/controllers/__init__.py
jtmorrisbytes/controllers/dummy_file.c
jtmorrisbytes/controllers/dummy_file.cp37-win_amd64.pyd
jtmorrisbytes/factories/__init__.py
jtmorrisbytes/factories/appfactory.c
jtmorrisbytes/factories/appfactory.cp37-win_amd64.pyd
jtmorrisbytes/factories/appfactory.py
jtmorrisbytes/models/__init__.py
jtmorrisbytes/models/base.c
jtmorrisbytes/models/base.cp37-win_amd64.pyd
jtmorrisbytes/models/base.py
jtmorrisbytes/views/__init__.py
jtmorrisbytes/views/dummy_file.c
jtmorrisbytes/views/dummy_file.cp37-win_amd64.pyd
jtmorrisbytes_flask_lib/flask/_compat.cp37-win_amd64.pyd
jtmorrisbytes_flask_lib/flask/app.cp37-win_amd64.pyd
jtmorrisbytes_flask_lib/flask/blueprints.cp37-win_amd64.pyd
jtmorrisbytes_flask_lib/flask/cli.cp37-win_amd64.pyd
jtmorrisbytes_flask_lib/flask/config.cp37-win_amd64.pyd
jtmorrisbytes_flask_lib/flask/ctx.cp37-win_amd64.pyd
jtmorrisbytes_flask_lib/flask/debughelpers.cp37-win_amd64.pyd
jtmorrisbytes_flask_lib/flask/globals.cp37-win_amd64.pyd
jtmorrisbytes_flask_lib/flask/helpers.cp37-win_amd64.pyd
pyjtmorrisbytes-0.1.6.dist-info/METADATA
pyjtmorrisbytes-0.1.6.dist-info/WHEEL
pyjtmorrisbytes-0.1.6.dist-info/top_level.txt
pyjtmorrisbytes-0.1.6.dist-info/RECORD
