Metadata-Version: 2.1
Name: pyjtmorrisbytes
Version: 0.1.6
Summary: flask-pyjtmorrisbytes-api
Home-page: https://www.jtmorrisbytes.com/
Author: Jordan Taylor Morris
Author-email: jthecybertinkerer@gmail.com
License: UNKNOWN
Platform: UNKNOWN
Requires-Python: ~=3.7
Requires-Dist: alabaster
Requires-Dist: aniso8601
Requires-Dist: astroid
Requires-Dist: atomicwrites
Requires-Dist: attrs
Requires-Dist: Babel
Requires-Dist: certifi
Requires-Dist: chardet
Requires-Dist: Click
Requires-Dist: colorama
Requires-Dist: Cython (>=0.29.4)
Requires-Dist: docutils
Requires-Dist: Flask
Requires-Dist: Flask-RESTful
Requires-Dist: flask-restplus
Requires-Dist: Flask-SQLAlchemy
Requires-Dist: hypothesis
Requires-Dist: idna
Requires-Dist: imagesize
Requires-Dist: isort
Requires-Dist: itsdangerous
Requires-Dist: Jinja2
Requires-Dist: jsonschema
Requires-Dist: lazy-object-proxy
Requires-Dist: MarkupSafe
Requires-Dist: mccabe
Requires-Dist: mimerender
Requires-Dist: more-itertools
Requires-Dist: packaging
Requires-Dist: pep8
Requires-Dist: pluggy
Requires-Dist: py
Requires-Dist: Pygments
Requires-Dist: pylint
Requires-Dist: pyparsing
Requires-Dist: pytest
Requires-Dist: pytest-cython
Requires-Dist: python-dateutil
Requires-Dist: python-mimeparse
Requires-Dist: pytz
Requires-Dist: requests
Requires-Dist: six
Requires-Dist: snowballstemmer
Requires-Dist: Sphinx
Requires-Dist: sphinxcontrib-websupport
Requires-Dist: SQLAlchemy
Requires-Dist: urllib3
Requires-Dist: waitress
Requires-Dist: Werkzeug
Requires-Dist: wrapt
Requires-Dist: tox
Requires-Dist: twine
Requires-Dist: setupmeta
